Workbook

Sheet INSTRUCTIONS
A1: JEWELRY INVENTORY SYSTEM - USER GUIDE
A3: GETTING STARTED
A4: This workbook helps you manage your jewelry business inventory with ease.
A6: SHEET OVERVIEW
A7: 1. Finished Inventory | B7: Your completed jewelry pieces ready for sale
A8: 2. Raw Materials | B8: Track chains, gemstones, findings, and other supplies
A9: 3. Spool Tracker | B9: Monitor chain/wire spools and remaining material
A10: 4. Usage Log | B10: Record when you cut material from spools
A11: 5. Bundle Builder | B11: Create custom bundles by entering SKUs
A12: 6. Search & Filter | B12: Quick stats and search tools
A14: HOW TO USE THE SPOOL TRACKER
A15: Step 1: | B15: Add a new spool to the "Spool Tracker" sheet
A16: Step 2: | B16: Enter Original Length and Current Length (both start the same)
A17: Step 3: | B17: When you cut material, log it in the "Usage Log" sheet
A18: Step 4: | B18: Update the "Current Length" in Spool Tracker
B19: The "Used" column will automatically calculate how much you've used
A21: HOW TO ADD NEW FINISHED INVENTORY
A22: Step 1: | B22: Go to "Finished Inventory" sheet
A23: Step 2: | B23: Find the next empty row
A24: Step 3: | B24: Enter SKU, Category, Name, Description
A25: Step 4: | B25: Enter Metal, Size, Price, and Cost (in BLUE cells)
B26: Profit and Margin % will calculate automatically
A28: HOW TO CREATE BUNDLES
A29: Step 1: | B29: Go to "Bundle Builder" sheet
A30: Step 2: | B30: Enter a Bundle Name
A31: Step 3: | B31: Type SKUs from your inventory in the SKU column
B32: Item details will auto-fill from your inventory
A33: Step 4: | B33: Set a discount % if desired
A34: Step 5: | B34: Toggle "Yes/No" to include/exclude items
A36: COLOR CODING
A37: BLUE text | B37: Input cells - enter your data here
A38: BLACK text | B38: Calculated formulas - do not edit
A39: GREEN text | B39: Links to other sheets in this workbook
A41: TIPS
A42: • Use Excel's AutoFilter (Data > Filter) for advanced searching
A43: • Each finished piece should have a unique SKU
A44: • Keep Cost data updated for accurate profit tracking
A45: • Tags column can hold keywords for easier searching

Sheet Finished Inventory
A1: SKU | B1: Category | C1: Name | D1: Description | E1: Metal | F1: Size | G1: Price | H1: MSRP | I1: Cost | J1: Profit | K1: Margin % | L1: Notes | M1: Images | N1: Tags | P1: VIEW IMAGES →
A2: BRAC_PP10 | B2: bracelet | C2: Bracelet - Photo Print 10 | D2: Photo Print ID: Photo Print 10 | J2: =IF(AND(G2<>"",I2<>""),G2-I2,"") | K2: =IF(AND(G2<>"",G2<>0),J2/G2,"") | L2: Photo Print: Photo Print 10 | M2: https://cdn.shopify.com/s/files/1/0936/8656/3183/files/PXL_20250819_174325341.jpg?v=1761563364 | P2: To view images: Click the URL in column M, or right-click > Open Hyperlink
A3: BRAC_PP20 | B3: bracelet | C3: Bracelet - Photo Print 20 | D3: Photo Print ID: Photo Print 20 | J3: =IF(AND(G3<>"",I3<>""),G3-I3,"") | K3: =IF(AND(G3<>"",G3<>0),J3/G3,"") | L3: Photo Print: Photo Print 20 | M3: https://cdn.shopify.com/s/files/1/0936/8656/3183/files/PXL_20250819_174912278.jpg?v=1761563366
A4: BRAC_PP39 | B4: bracelet | C4: Bracelet - Photo Print 39 | D4: Photo Print ID: Photo Print 39 | J4: =IF(AND(G4<>"",I4<>""),G4-I4,"") | K4: =IF(AND(G4<>"",G4<>0),J4/G4,"") | L4: Photo Print: Photo Print 39 | M4: https://cdn.shopify.com/s/files/1/0936/8656/3183/files/PXL_20250819_174623882.jpg?v=1761563376
A5: BRAC_PP4 | B5: bracelet | C5: Bracelet - Photo Print 4 | D5: Photo Print ID: Photo Print 4 | J5: =IF(AND(G5<>"",I5<>""),G5-I5,"") | K5: =IF(AND(G5<>"",G5<>0),J5/G5,"") | L5: Photo Print: Photo Print 4 | M5: https://cdn.shopify.com/s/files/1/0936/8656/3183/files/PXL_20250819_193636787.jpg?v=1761563362
A6: BRAC_PP40 | B6: bracelet | C6: Bracelet - Photo Print 40 | D6: Photo Print ID: Photo Print 40 | J6: =IF(AND(G6<>"",I6<>""),G6-I6,"") | K6: =IF(AND(G6<>"",G6<>0),J6/G6,"") | L6: Photo Print: Photo Print 40 | M6: https://cdn.shopify.com/s/files/1/0936/8656/3183/files/PXL_20250819_193703743.jpg?v=1761563376
A7: BRAC_PP42 | B7: bracelet | C7: Bracelet - Photo Print 42 | D7: Photo Print ID: Photo Print 42 | J7: =IF(AND(G7<>"",I7<>""),G7-I7,"") | K7: =IF(AND(G7<>"",G7<>0),J7/G7,"") | L7: Photo Print: Photo Print 42 | M7: https://cdn.shopify.com/s/files/1/0936/8656/3183/files/PXL_20250819_194028193.jpg?v=1761563376
A8: BRAC_PP43 | B8: bracelet | C8: Bracelet - Photo Print 43 | D8: Photo Print ID: Photo Print 43 | J8: =IF(AND(G8<>"",I8<>""),G8-I8,"") | K8: =IF(AND(G8<>"",G8<>0),J8/G8,"") | L8: Photo Print: Photo Print 43 | M8: https://cdn.shopify.com/s/files/1/0936/8656/3183/files/PXL_20250819_174809086.jpg?v=1761563377
A9: BRAC_PP432 | B9: bracelet | C9: Bracelet - Photo Print 432 | D9: Photo Print ID: Photo Print 432 | J9: =IF(AND(G9<>"",I9<>""),G9-I9,"") | K9: =IF(AND(G9<>"",G9<>0),J9/G9,"") | L9: Photo Print: Photo Print 432 | M9: https://cdn.shopify.com/s/files/1/0936/8656/3183/files/necklace6.jpg?v=1764260388
A10: BRAC_PP45 | B10: bracelet | C10: Bracelet - Photo Print 45 | D10: Photo Print ID: Photo Print 45 | J10: =IF(AND(G10<>"",I10<>""),G10-I10,"") | K10: =IF(AND(G10<>"",G10<>0),J10/G10,"") | L10: Photo Print: Photo Print 45 | M10: https://cdn.shopify.com/s/files/1/0936/8656/3183/files/PXL_20250819_193925175.jpg?v=1761563377
A11: BRAC_PP46 | B11: bracelet | C11: Bracelet - Photo Print 46 | D11: Photo Print ID: Photo Print 46 | J11: =IF(AND(G11<>"",I11<>""),G11-I11,"") | K11: =IF(AND(G11<>"",G11<>0),J11/G11,"") | L11: Photo Print: Photo Print 46 | M11: https://cdn.shopify.com/s/files/1/0936/8656/3183/files/PXL_20250819_174217542.jpg?v=1761563377
A12: BRAC_PP47 | B12: bracelet | C12: Bracelet - Photo Print 47 | D12: Photo Print ID: Photo Print 47 | J12: =IF(AND(G12<>"",I12<>""),G12-I12,"") | K12: =IF(AND(G12<>"",G12<>0),J12/G12,"") | L12: Photo Print: Photo Print 47 | M12: https://cdn.shopify.com/s/files/1/0936/8656/3183/files/PXL_20250819_194112806.jpg?v=1761563377
A13: BRAC_PP48 | B13: bracelet | C13: Bracelet - Photo Print 48 | D13: Photo Print ID: Photo Print 48 | J13: =IF(AND(G13<>"",I13<>""),G13-I13,"") | K13: =IF(AND(G13<>"",G13<>0),J13/G13,"") | L13: Photo Print: Photo Print 48 | M13: https://cdn.shopify.com/s/files/1/0936/8656/3183/files/PXL_20250819_175142414.jpg?v=1761563377
A14: BRAC_PP49 | B14: bracelet | C14: Bracelet - Photo Print 49 | D14: Photo Print ID: Photo Print 49 | J14: =IF(AND(G14<>"",I14<>""),G14-I14,"") | K14: =IF(AND(G14<>"",G14<>0),J14/G14,"") | L14: Photo Print: Photo Print 49 | M14: https://cdn.shopify.com/s/files/1/0936/8656/3183/files/PXL_20250819_175715094.jpg?v=1761563377
... A51: BRAC_PP9 | B51: bracelet | C51: Bracelet - Photo Print 9 | D51: Photo Print ID: Photo Print 9 | J51: =IF(AND(G51<>"",I51<>""),G51-I51,"") | K51: =IF(AND(G51<>"",G51<>0),J51/G51,"") | L51: Photo Print: Photo Print 9 | M51: https://cdn.shopify.com/s/files/1/0936/8656/3183/files/PXL_20250819_173937234.jpg?v=1761563364
A52: PIID000016 | B52: bracelet | C52: 4mm MoissaniteTennis Bracelet | D52: 925 18 CTW 4mm moissanite tennis bracelet | E52: 925 Sterling Silver | F52: size 8 | I52: 25 | J52: =IF(AND(G52<>"",I52<>""),G52-I52,"") | K52: =IF(AND(G52<>"",G52<>0),J52/G52,"")
A53: PIID000017 | B53: bracelet | C53: 3 stone saphire gold bracelet | D53: 3 saphire stone 14k hinge bracelet | F53: size 8 | I53: 0 | J53: =IF(AND(G53<>"",I53<>""),G53-I53,"") | K53: =IF(AND(G53<>"",G53<>0),J53/G53,"")
A54: PIID000018 | B54: bracelet | C54: Cubic Zirconia tennis bracelet | D54: 24 CTW cubic zirconia tennis bracelet | F54: size 7 | I54: 0 | J54: =IF(AND(G54<>"",I54<>""),G54-I54,"") | K54: =IF(AND(G54<>"",G54<>0),J54/G54,"")
A55: PIID000019 | B55: bracelet | C55: 14 k gold bracelet | D55: 14 k gold bracelet size 7 | E55: Gold | F55: size 7 | I55: 0 | J55: =IF(AND(G55<>"",I55<>""),G55-I55,"") | K55: =IF(AND(G55<>"",G55<>0),J55/G55,"")
A56: PIID000020 | B56: bracelet | C56: 12k plated 925 7 stone bracelet | D56: 12k over 925. 7 glass faux diamond bracelet | E56: 925 Sterling Silver | F56: size 7.5 | J56: =IF(AND(G56<>"",I56<>""),G56-I56,"") | K56: =IF(AND(G56<>"",G56<>0),J56/G56,"")
A57: PIID000022 | B57: bracelet | C57: 2 tone diamond cut 925 | D57: 925 diamond cut 2 tone twist chain | E57: 925 Sterling Silver | F57: size 7 | I57: 25 | J57: =IF(AND(G57<>"",I57<>""),G57-I57,"") | K57: =IF(AND(G57<>"",G57<>0),J57/G57,"")
A58: EAR_MOISS_DROP | B58: earring | C58: Moissanite Drop Earrings | D58: Photo Print ID: Moissanite drop earrings | J58: =IF(AND(G58<>"",I58<>""),G58-I58,"") | K58: =IF(AND(G58<>"",G58<>0),J58/G58,"") | L58: Photo Print: Moissanite drop earrings | M58: https://cdn.shopify.com/s/files/1/0936/8656/3183/files/PC000023.jpg?v=1764408730
A59: EAR_PP257 | B59: earring | C59: Earrings - Photo Print 257 | D59: Photo Print ID: Photo Print 257 | J59: =IF(AND(G59<>"",I59<>""),G59-I59,"") | K59: =IF(AND(G59<>"",G59<>0),J59/G59,"") | L59: Photo Print: Photo Print 257 | M59: https://cdn.shopify.com/s/files/1/0936/8656/3183/files/PXL_20251108_040536996.jpg?v=1762842149
A60: EAR_PP259 | B60: earring | C60: Earrings - Photo Print 259 | D60: Photo Print ID: Photo Print 259 | J60: =IF(AND(G60<>"",I60<>""),G60-I60,"") | K60: =IF(AND(G60<>"",G60<>0),J60/G60,"") | L60: Photo Print: Photo Print 259 | M60: https://cdn.shopify.com/s/files/1/0936/8656/3183/files/PXL_20251108_040704002.jpg?v=1762842149
A61: EAR_PP261 | B61: earring | C61: Earrings - Photo Print 261 | D61: Photo Print ID: Photo Print 261 | J61: =IF(AND(G61<>"",I61<>""),G61-I61,"") | K61: =IF(AND(G61<>"",G61<>0),J61/G61,"") | L61: Photo Print: Photo Print 261 | M61: https://cdn.shopify.com/s/files/1/0936/8656/3183/files/PXL_20251108_040710433.jpg?v=1762842150
A62: EAR_PP263 | B62: earring | C62: Earrings - Photo Print 263 | D62: Photo Print ID: Photo Print 263 | J62: =IF(AND(G62<>"",I62<>""),G62-I62,"") | K62: =IF(AND(G62<>"",G62<>0),J62/G62,"") | L62: Photo Print: Photo Print 263 | M62: https://cdn.shopify.com/s/files/1/0936/8656/3183/files/PXL_20251108_040139833.jpg?v=1762842150
A63: EAR_PP280 | B63: earring | C63: Earrings - Photo Print 280 | D63: Photo Print ID: Photo Print 280 | J63: =IF(AND(G63<>"",I63<>""),G63-I63,"") | K63: =IF(AND(G63<>"",G63<>0),J63/G63,"") | L63: Photo Print: Photo Print 280 | M63: https://cdn.shopify.com/s/files/1/0936/8656/3183/files/PXL_20251108_040710433_b5b22ba0-df8f-4c1c-9420-452483e97f22.jpg?v=1762842153
A64: EAR_PP287 | B64: earring | C64: Earrings - Photo Print 287 | D64: Photo Print ID: Photo Print 287 | J64: =IF(AND(G64<>"",I64<>""),G64-I64,"") | K64: =IF(AND(G64<>"",G64<>0),J64/G64,"") | L64: Photo Print: Photo Print 287 | M64: https://cdn.shopify.com/s/files/1/0936/8656/3183/files/PXL_20251108_040221416.jpg?v=1762842153
A65: EAR_PP291 | B65: earring | C65: Earrings - Photo Print 291 | D65: Photo Print ID: Photo Print 291 | J65: =IF(AND(G65<>"",I65<>""),G65-I65,"") | K65: =IF(AND(G65<>"",G65<>0),J65/G65,"") | L65: Photo Print: Photo Print 291 | M65: https://cdn.shopify.com/s/files/1/0936/8656/3183/files/PXL_20251108_040536996_848b69f9-9d7a-4128-9910-4b318ec32693.jpg?v=1762842153
A66: EAR_PP292 | B66: earring | C66: Earrings - Photo Print 292 | D66: Photo Print ID: Photo Print 292 | J66: =IF(AND(G66<>"",I66<>""),G66-I66,"") | K66: =IF(AND(G66<>"",G66<>0),J66/G66,"") | L66: Photo Print: Photo Print 292 | M66: https://cdn.shopify.com/s/files/1/0936/8656/3183/files/PXL_20251108_040704002_5f2fa9e7-f049-4444-96fe-962507ec58bc.jpg?v=1762842153
A67: EAR_PP297 | B67: earring | C67: Earrings - Photo Print 297 | D67: Photo Print ID: Photo Print 297 | J67: =IF(AND(G67<>"",I67<>""),G67-I67,"") | K67: =IF(AND(G67<>"",G67<>0),J67/G67,"") | L67: Photo Print: Photo Print 297 | M67: https://cdn.shopify.com/s/files/1/0936/8656/3183/files/PXL_20251108_042407875.jpg?v=1762842154
A68: EAR_PP299 | B68: earring | C68: Earrings - Photo Print 299 | D68: Photo Print ID: Photo Print 299 | J68: =IF(AND(G68<>"",I68<>""),G68-I68,"") | K68: =IF(AND(G68<>"",G68<>0),J68/G68,"") | L68: Photo Print: Photo Print 299 | M68: https://cdn.shopify.com/s/files/1/0936/8656/3183/files/PXL_20251108_040221416_23019738-cc17-4575-991a-fc5e788baf0d.jpg?v=1762842155
A69: EAR_PP300 | B69: earring | C69: Earrings - Photo Print 300 | D69: Photo Print ID: Photo Print 300 | J69: =IF(AND(G69<>"",I69<>""),G69-I69,"") | K69: =IF(AND(G69<>"",G69<>0),J69/G69,"") | L69: Photo Print: Photo Print 300 | M69: https://cdn.shopify.com/s/files/1/0936/8656/3183/files/PXL_20251108_040139833_e6e05fb8-d499-43ef-a509-fd46954be110.jpg?v=1762842155
... A87: EAR_PP396 | B87: earring | C87: Earrings - Photo Print 396 | D87: Photo Print ID: Photo Print 396 | J87: =IF(AND(G87<>"",I87<>""),G87-I87,"") | K87: =IF(AND(G87<>"",G87<>0),J87/G87,"") | L87: Photo Print: Photo Print 396 | M87: https://cdn.shopify.com/s/files/1/0936/8656/3183/files/PC000021.jpg?v=1764408401
A88: PIID000013 | B88: earring | C88: .5 CTW | D88: 925 .5CTW stud earrings | E88: 925 Sterling Silver | F88: na | I88: 0 | J88: =IF(AND(G88<>"",I88<>""),G88-I88,"") | K88: =IF(AND(G88<>"",G88<>0),J88/G88,"")
A89: PIID000014 | B89: earring | C89: 2 CTW | D89: Stainless Steal 2 CTW cubic zirconia stud | F89: na | I89: 0 | J89: =IF(AND(G89<>"",I89<>""),G89-I89,"") | K89: =IF(AND(G89<>"",G89<>0),J89/G89,"")
A90: PIID000015 | B90: earring | C90: 1.5 CTW Moissanite | D90: 14k white gold over 925 1.5 CTW moissanite flower stud | E90: 925 Sterling Silver | F90: na | I90: 25 | J90: =IF(AND(G90<>"",I90<>""),G90-I90,"") | K90: =IF(AND(G90<>"",G90<>0),J90/G90,"")
A91: PIID000023 | B91: earring | C91: 1/4 CTW Diamond Stud | D91: 1/4 CTW 14k white gold Diamond Stud | E91: Gold | F91: na | H91: 125 | I91: 0 | J91: =IF(AND(G91<>"",I91<>""),G91-I91,"") | K91: =IF(AND(G91<>"",G91<>0),J91/G91,"")
A92: PIID000024 | B92: earring | C92: 1/2 CTW Diamond Stud | D92: 1/2 CTW 14k White gold Diamond Stud | E92: Gold | F92: na | H92: 350 | I92: 0 | J92: =IF(AND(G92<>"",I92<>""),G92-I92,"") | K92: =IF(AND(G92<>"",G92<>0),J92/G92,"")
A93: PIID000025 | B93: earring | C93: Baguette solitaire emerald and natural diamond hoop earringws 14k yellow gold | D93: 14k yellow gold natural diamond hoop emerald drop | E93: Gold | F93: na | H93: 780 | I93: 25 | J93: =IF(AND(G93<>"",I93<>""),G93-I93,"") | K93: =IF(AND(G93<>"",G93<>0),J93/G93,"")
A94: PIID000030 | B94: earring | C94: vintage 925 mexico blue topaz with opal or moonstone teardrop dangle | D94: Mexico 925, Blue topaz and moonstone or opal | E94: 925 Sterling Silver | F94: na | H94: 260 | I94: 1.5 | J94: =IF(AND(G94<>"",I94<>""),G94-I94,"") | K94: =IF(AND(G94<>"",G94<>0),J94/G94,"")
A95: NECK_10K_FILLED_YELLOW_GO | B95: necklace | C95: 10k filled yellow gold rolled chain necklace | D95: Identifier: 10k filled yellow gold rolled chain necklace | J95: =IF(AND(G95<>"",I95<>""),G95-I95,"") | K95: =IF(AND(G95<>"",G95<>0),J95/G95,"") | L95: 10k filled yellow gold rolled chain necklace | M95: https://cdn.shopify.com/s/files/1/0936/8656/3183/files/2025-08-13-15-11-39-175.jpg?v=1764403527
A96: NECK_10K_GOLD_FILLED_12_N | B96: necklace | C96: 10k gold filled, 12" necklace | D96: Identifier: 10k gold filled, 12" necklace | J96: =IF(AND(G96<>"",I96<>""),G96-I96,"") | K96: =IF(AND(G96<>"",G96<>0),J96/G96,"") | L96: 10k gold filled, 12" necklace | M96: https://cdn.shopify.com/s/files/1/0936/8656/3183/files/2025-08-13-15-12-03-573_1a0c48e4-f63d-46e3-babe-f90043d3ac97.jpg?v=1764403911
A97: NECK_16_GOLD_DIAMOND_CUT_ | B97: necklace | C97: 16" gold diamond cut chain | D97: Identifier: 16" gold diamond cut chain | J97: =IF(AND(G97<>"",I97<>""),G97-I97,"") | K97: =IF(AND(G97<>"",G97<>0),J97/G97,"") | L97: 16" gold diamond cut chain | M97: https://cdn.shopify.com/s/files/1/0936/8656/3183/files/2025-08-13-15-12-34-200.jpg?v=1764404329
A98: NECK_ARTISAN_MURANO_GLASS | B98: necklace | C98: Artisan-Murano Glass | D98: Identifier: Artisan-Murano Glass | J98: =IF(AND(G98<>"",I98<>""),G98-I98,"") | K98: =IF(AND(G98<>"",G98<>0),J98/G98,"") | L98: Artisan-Murano Glass | M98: https://cdn.shopify.com/s/files/1/0936/8656/3183/files/2025-08-13-15-13-23-968.jpg?v=1763457333
A99: NECK_BOHO_1000013 | B99: necklace | C99: Boho-1000013 | D99: Identifier: Boho-1000013 | J99: =IF(AND(G99<>"",I99<>""),G99-I99,"") | K99: =IF(AND(G99<>"",G99<>0),J99/G99,"") | L99: Boho-1000013 | M99: https://cdn.shopify.com/s/files/1/0936/8656/3183/files/PC000031.jpg?v=1763455154
A100: NECK_FASHION_1000016 | B100: necklace | C100: fashion-1000016 | D100: Identifier: fashion-1000016 | J100: =IF(AND(G100<>"",I100<>""),G100-I100,"") | K100: =IF(AND(G100<>"",G100<>0),J100/G100,"") | L100: fashion-1000016 | M100: https://cdn.shopify.com/s/files/1/0936/8656/3183/files/PC000030.jpg?v=1763455352
A101: NECK_FASHION___1000014 | B101: necklace | C101: fashion - 1000014 | D101: Identifier: fashion - 1000014 | J101: =IF(AND(G101<>"",I101<>""),G101-I101,"") | K101: =IF(AND(G101<>"",G101<>0),J101/G101,"") | L101: fashion - 1000014 | M101: https://cdn.shopify.com/s/files/1/0936/8656/3183/files/2025-08-13-15-14-58-252.jpg?v=1763455281
A102: NECK_N1 | B102: necklace | C102: N1 | D102: Identifier: N1 | J102: =IF(AND(G102<>"",I102<>""),G102-I102,"") | K102: =IF(AND(G102<>"",G102<>0),J102/G102,"") | L102: N1 | M102: https://cdn.shopify.com/s/files/1/0936/8656/3183/files/necklace.jpg?v=1764260282
A103: NECK_N10 | B103: necklace | C103: Necklace N10 | D103: Identifier: n10 | J103: =IF(AND(G103<>"",I103<>""),G103-I103,"") | K103: =IF(AND(G103<>"",G103<>0),J103/G103,"") | L103: n10 | M103: https://cdn.shopify.com/s/files/1/0936/8656/3183/files/necklace11.jpg?v=1764260488
A104: NECK_N11 | B104: necklace | C104: Necklace N11 | D104: Identifier: n11 | J104: =IF(AND(G104<>"",I104<>""),G104-I104,"") | K104: =IF(AND(G104<>"",G104<>0),J104/G104,"") | L104: n11 | M104: https://cdn.shopify.com/s/files/1/0936/8656/3183/files/2025-08-13-15-22-23-452.jpg?v=1762900134
A105: NECK_N13 | B105: necklace | C105: Necklace N13 | D105: Identifier: n13 | J105: =IF(AND(G105<>"",I105<>""),G105-I105,"") | K105: =IF(AND(G105<>"",G105<>0),J105/G105,"") | L105: n13 | M105: https://cdn.shopify.com/s/files/1/0936/8656/3183/files/2025-08-13-15-30-17-387.jpg?v=1764203257
A106: NECK_N2 | B106: necklace | C106: Necklace N2 | D106: Identifier: n2 | J106: =IF(AND(G106<>"",I106<>""),G106-I106,"") | K106: =IF(AND(G106<>"",G106<>0),J106/G106,"") | L106: n2 | M106: https://cdn.shopify.com/s/files/1/0936/8656/3183/files/necklace2.jpg?v=1764260317
... A163: NECK_VINTAGE___1000013_(2 | B163: necklace | C163: vintage - 1000013 (2) | D163: Identifier: vintage - 1000013 (2) | J163: =IF(AND(G163<>"",I163<>""),G163-I163,"") | K163: =IF(AND(G163<>"",G163<>0),J163/G163,"") | L163: vintage - 1000013 (2) | M163: https://cdn.shopify.com/s/files/1/0936/8656/3183/files/2025-08-13-15-36-36-791.jpg?v=1763457129
A164: NK_AB_ | B164: necklace | C164: Artisan Beaded Multi-Strand: | D164: A three-strand piece featuring a mix of black faceted beads, clear crystals, and small pink accents. This appears to be an artisan piece due to the varied bead shapes and rhythmic pattern. | E164: Mixed Materials | G164: 135 | J164: =IF(AND(G164<>"",I164<>""),G164-I164,"") | K164: =IF(AND(G164<>"",G164<>0),J164/G164,"") | L164: SKU: NK-AB-
A165: NK_AG_ | B165: necklace | C165: Amber Glass Lariat: | D165: Amber Glass Lariat: Artisan Handcrafted Amber Glass Teardrop Pendant on Cord Lariat Necklace. | J165: =IF(AND(G165<>"",I165<>""),G165-I165,"") | K165: =IF(AND(G165<>"",G165<>0),J165/G165,"") | L165: SKU: NK-AG-
A166: NK_AP_ST_083 | B166: necklace | C166: Animal Print Chunky | D166: Black & mixed leopard/zebra print focal bead necklace. | G166: 33 | J166: =IF(AND(G166<>"",I166<>""),G166-I166,"") | K166: =IF(AND(G166<>"",G166<>0),J166/G166,"") | L166: SKU: NK-AP-ST-083
A167: NK_BF_ | B167: necklace | C167: Blue Filigree Silver Y-Necklace: | D167: Delicate Silver-Tone Filigree Y-Necklace with Blue Stone Accents. | J167: =IF(AND(G167<>"",I167<>""),G167-I167,"") | K167: =IF(AND(G167<>"",G167<>0),J167/G167,"") | L167: SKU: NK-BF-
A168: NK_BG | B168: necklace | C168: Blue Glass Bead Double Strand: | D168: Vintage Double Strand Light Blue Faceted Glass Bead Choker Necklace. | E168: Mixed Materials | J168: =IF(AND(G168<>"",I168<>""),G168-I168,"") | K168: =IF(AND(G168<>"",G168<>0),J168/G168,"") | L168: SKU: NK-BG
A169: NK_BK_BE_012 | B169: necklace | C169: Vintage Multi-Strand Black & Silver Seed Bead Necklace | D169: Multi-strand cascading waterfall design with black and silver seed beads. | E169: Mixed Materials | G169: 32.5 | J169: =IF(AND(G169<>"",I169<>""),G169-I169,"") | K169: =IF(AND(G169<>"",G169<>0),J169/G169,"") | L169: 1980s style. Check for "925" for Liquid Silver value.
A170: NK_BK_BE_013 | B170: necklace | C170: Vintage 5-Strand Black Waterfall Focal Necklace | D170: 5-strand cascading necklace with faceted black beads and patterned focal points. | G170: 40 | J170: =IF(AND(G170<>"",I170<>""),G170-I170,"") | K170: =IF(AND(G170<>"",G170<>0),J170/G170,"") | L170: 1980s statement piece. Higher value if signed (e.g., Trifari).
A171: NK_BK_CL_086 | B171: necklace | C171: 80s Resin Bib | D171: Chunky asymmetrical black & clear resin link statement. | G171: 42.5 | J171: =IF(AND(G171<>"",I171<>""),G171-I171,"") | K171: =IF(AND(G171<>"",G171<>0),J171/G171,"") | L171: SKU: NK-BK-CL-086
A172: NK_BK_CP_088 | B172: necklace | C172: Venetian Lampwork | D172: Black heart pendant with copper swirls on seed beads. | G172: 55 | J172: =IF(AND(G172<>"",I172<>""),G172-I172,"") | K172: =IF(AND(G172<>"",G172<>0),J172/G172,"") | L172: SKU: NK-BK-CP-088
A173: NK_BK_GT_090 | B173: necklace | C173: Carved Black Focal | D173: Chunky carved matte black & gold-tone station bib. | G173: 36.5 | J173: =IF(AND(G173<>"",I173<>""),G173-I173,"") | K173: =IF(AND(G173<>"",G173<>0),J173/G173,"") | L173: SKU: NK-BK-GT-090
A174: NK_BK_PD_032 | B174: necklace | C174: Black Bead Y-Necklace with Leaf Tassel Drop | D174: Black bead chain with a tiered drop and three silver-tone leaf charms. | E174: Mixed Materials | G174: 27.5 | J174: =IF(AND(G174<>"",I174<>""),G174-I174,"") | K174: =IF(AND(G174<>"",G174<>0),J174/G174,"") | L174: Nature-inspired Y2K/Vintage style.
A175: NK_BK_ST_031 | B175: necklace | C175: Beaded Black & Silver Striped Necktie Necklace | D175: Hand-beaded necktie shape with diagonal monochrome stripes. | E175: Mixed Materials | G175: 50 | J175: =IF(AND(G175<>"",I175<>""),G175-I175,"") | K175: =IF(AND(G175<>"",G175<>0),J175/G175,"") | L175: Dramatic 80s "power dressing" accessory.
A176: NK_BK_ST_033 | B176: necklace | C176: Chunky Black Organic Stone Statement Necklace | D176: Large polished black "river rock" stones with faceted metallic spacers. | G176: 40 | J176: =IF(AND(G176<>"",I176<>""),G176-I176,"") | K176: =IF(AND(G176<>"",G176<>0),J176/G176,"") | L176: Bold Boho-Chic aesthetic. Check for genuine onyx.
A177: NK_BK_ST_037 | B177: necklace | C177: Hematite-Style Necklace with Silver Filigree Caps | D177: Double strand of high-luster black beads with antiqued filigree caps. | G177: 45 | J177: =IF(AND(G177<>"",I177<>""),G177-I177,"") | K177: =IF(AND(G177<>"",G177<>0),J177/G177,"") | L177: Victorian Revival style. Higher value if signed.
A178: NK_BK_ST_082 | B178: necklace | C178: 80s Black Seed Bead | D178: Dramatic 10+ strand black seed bead & sphere collar. | E178: Mixed Materials | G178: 28.5 | J178: =IF(AND(G178<>"",I178<>""),G178-I178,"") | K178: =IF(AND(G178<>"",G178<>0),J178/G178,"") | L178: SKU: NK-BK-ST-082
A179: NK_BL_AB_097 | B179: necklace | C179: Blue AB Crystal | D179: 1950s graduated blue Aurora Borealis glass necklace. | G179: 50 | J179: =IF(AND(G179<>"",I179<>""),G179-I179,"") | K179: =IF(AND(G179<>"",G179<>0),J179/G179,"") | L179: SKU: NK-BL-AB-097
A180: NK_BL_BE_027 | B180: necklace | C180: Vintage Blue & Gold Multi-Media Station Necklace | D180: Long strand with faceted glass, frosted resin, and turquoise-style beads. | G180: 37.5 | J180: =IF(AND(G180<>"",I180<>""),G180-I180,"") | K180: =IF(AND(G180<>"",G180<>0),J180/G180,"") | L180: Eclectic Boho-Chic style from the 90s/00s.
A181: NK_BR_TQ_095 | B181: necklace | C181: Brass Fan Bib | D181: Geometric brass fans with turquoise-style inlays. | G181: 36.5 | J181: =IF(AND(G181<>"",I181<>""),G181-I181,"") | K181: =IF(AND(G181<>"",G181<>0),J181/G181,"") | L181: SKU: NK-BR-TQ-095
A182: NK_BS_ | B182: necklace | C182: Black Seed Bead Multi-Strand: | D182: Modern Four-Strand Black Seed Bead Draped Statement Necklace. | E182: Mixed Materials | J182: =IF(AND(G182<>"",I182<>""),G182-I182,"") | K182: =IF(AND(G182<>"",G182<>0),J182/G182,"") | L182: SKU: NK-BS-
A183: NK_BW_ | B183: necklace | C183: Blue and White Stone Fringe: | D183: A striking two-strand necklace with vertical "fringe" stones in shades of light blue and white. The raw, rectangular shapes of the stones give it a modern, handcrafted look. | G183: 110 | J183: =IF(AND(G183<>"",I183<>""),G183-I183,"") | K183: =IF(AND(G183<>"",G183<>0),J183/G183,"") | L183: SKU: NK-BW-
A184: NK_BW_ST_036 | B184: necklace | C184: Black & White Geometric Striped Bead Necklace | D184: Monochrome strand with black faceted beads and striped focal spacers. | E184: Mixed Materials | G184: 31.5 | J184: =IF(AND(G184<>"",I184<>""),G184-I184,"") | K184: =IF(AND(G184<>"",G184<>0),J184/G184,"") | L184: Retro 80s/90s Mod revival aesthetic.
A185: NK_CM | B185: necklace | C185: Cream Multi-Strand Pearl: | D185: Vintage Mid-Century Triple Strand Cream Faux Pearl Necklace with Crystal Accents. | J185: =IF(AND(G185<>"",I185<>""),G185-I185,"") | K185: =IF(AND(G185<>"",G185<>0),J185/G185,"") | L185: SKU: NK-CM
A186: NK_CT_ | B186: necklace | C186: Classic Triple-Strand Pink Pearl: | D186: A vintage-style triple strand of uniform light-pink faux pearls. This is a timeless design often seen in mid-century fashion. | G186: 27.5 | J186: =IF(AND(G186<>"",I186<>""),G186-I186,"") | K186: =IF(AND(G186<>"",G186<>0),J186/G186,"") | L186: SKU: NK-CT-
A187: NK_CW_ | B187: necklace | C187: Classic White Pearl Single Strand: | D187: Timeless Single Strand White Faux Pearl Princess Length Necklace. | J187: =IF(AND(G187<>"",I187<>""),G187-I187,"") | K187: =IF(AND(G187<>"",G187<>0),J187/G187,"") | L187: SKU: NK-CW-
A188: NK_DR_ | B188: necklace | C188: Deep Red & Cream Double Strand: | D188: Classic Double Strand Red and Cream Seed Bead Minimalist Necklace. | J188: =IF(AND(G188<>"",I188<>""),G188-I188,"") | K188: =IF(AND(G188<>"",G188<>0),J188/G188,"") | L188: SKU: NK-DR-
A189: NK_ET_MM_038 | B189: necklace | C189: Mixed Media Earth Tone Tassel Necklace | D189: Long strand with jasper-style beads, butterfly charm, and intaglio tassel. | G189: 90 | J189: =IF(AND(G189<>"",I189<>""),G189-I189,"") | K189: =IF(AND(G189<>"",G189<>0),J189/G189,"") | L189: Elaborate artisan "boho" statement piece.
A190: NK_FD | B190: necklace | C190: Floral Decal Oval Beads | D190: Artisan Vintage-Style Cream Oval Beads with Painted Floral Decals and Gold Spacers. | E190: Mixed Materials | J190: =IF(AND(G190<>"",I190<>""),G190-I190,"") | K190: =IF(AND(G190<>"",G190<>0),J190/G190,"") | L190: SKU: NK-FD
A191: NK_GF_PD_003 | B191: necklace | C191: Vintage Gold Tone Honey Amber Pendant Necklace | D191: Geometric triangular honey-amber stone in a gold-tone bezel setting. | E191: Gold Tone | G191: 50 | J191: =IF(AND(G191<>"",I191<>""),G191-I191,"") | K191: =IF(AND(G191<>"",G191<>0),J191/G191,"") | L191: 1970s Modernist style. Genuine Amber values higher.
A192: NK_GN_PL_100 | B192: necklace | C192: Green Jade Strand | D192: Vintage light green jadeite/nephrite bead necklace. | G192: 92.5 | J192: =IF(AND(G192<>"",I192<>""),G192-I192,"") | K192: =IF(AND(G192<>"",G192<>0),J192/G192,"") | L192: SKU: NK-GN-PL-100
A193: NK_GP_ | B193: necklace | C193: Graduated Pink Pearl Ombré: | D193: A four-strand statement necklace with faux pearls that transition from light blush to a deep rosy pink. The graduated strand lengths create a elegant draped effect. | G193: 55 | J193: =IF(AND(G193<>"",I193<>""),G193-I193,"") | K193: =IF(AND(G193<>"",G193<>0),J193/G193,"") | L193: SKU: NK-GP-
A194: NK_GT_BS_091 | B194: necklace | C194: Brushed Gold Bead | D194: Mid-Century double-strand satin finish gold beads. | E194: Mixed Materials | G194: 50 | J194: =IF(AND(G194<>"",I194<>""),G194-I194,"") | K194: =IF(AND(G194<>"",G194<>0),J194/G194,"") | L194: SKU: NK-GT-BS-091
A195: NK_GT_CH_025 | B195: necklace | C195: Vintage Double Row Gold-Tone Box Link Necklace | D195: Substantial necklace with two parallel rows of textured box links. | E195: Gold Tone | G195: 45 | J195: =IF(AND(G195<>"",I195<>""),G195-I195,"") | K195: =IF(AND(G195<>"",G195<>0),J195/G195,"") | L195: 1970s/80s maximalist aesthetic.
A196: NK_GT_PD_005 | B196: necklace | C196: Vintage Gold Tone Double Panther Head Necklace | D196: Statement "door knocker" design with two panther heads on a flat mesh chain. | E196: Gold Tone | G196: 65 | J196: =IF(AND(G196<>"",I196<>""),G196-I196,"") | K196: =IF(AND(G196<>"",G196<>0),J196/G196,"") | L196: 1980s maximalist. High value if signed (e.g., KJL/Ciner).
A197: NK_GT_PD_017 | B197: necklace | C197: Vintage Gold Tone Multi-Color Station Necklace | D197: Multi-colored bezel-set cabochons (rainbow palette) on a gold-tone chain. | E197: Gold Tone | G197: 45 | J197: =IF(AND(G197<>"",I197<>""),G197-I197,"") | K197: =IF(AND(G197<>"",G197<>0),J197/G197,"") | L197: Y2K aesthetic. Common in vintage Chico’s collections.
A198: NK_GT_PD_020 | B198: necklace | C198: Vintage Gold Tone Hummingbird Circle Necklace | D198: Open-circle pendant with bird in flight and red rhinestone floral accent. | E198: Gold Tone | G198: 27.5 | J198: =IF(AND(G198<>"",I198<>""),G198-I198,"") | K198: =IF(AND(G198<>"",G198<>0),J198/G198,"") | L198: Nature-inspired; check back for "JJI" or "Avon" hallmarks.
A199: NK_GT_PD_030 | B199: necklace | C199: Vintage Enamel Seahorse Pendant on Rope Chain | D199: Textured gold-tone seahorse with multi-colored kiln-fired enamel. | G199: 47.5 | J199: =IF(AND(G199<>"",I199<>""),G199-I199,"") | K199: =IF(AND(G199<>"",G199<>0),J199/G199,"") | L199: Whimsical 70s nautical motif.
A200: NK_GT_PE_021 | B200: necklace | C200: Vintage Gold Tone Faux Pearl Station Necklace | D200: Dainty gold-tone chain with white round faux pearl "tin cup" stations. | E200: Gold Tone | G200: 26.5 | J200: =IF(AND(G200<>"",I200<>""),G200-I200,"") | K200: =IF(AND(G200<>"",G200<>0),J200/G200,"") | L200: Classic versatile style. Check for 14K marks.
A201: NK_GT_PE_022 | B201: necklace | C201: Vintage Double Strand Pearl with Amethyst Focal | D201: Double row of creamy faux pearls with an ornate gold-tone floral amethyst focal. | G201: 55 | J201: =IF(AND(G201<>"",I201<>""),G201-I201,"") | K201: =IF(AND(G201<>"",G201<>0),J201/G201,"") | L201: High-end mid-century costume piece.
A202: NK_GT_PE_023 | B202: necklace | C202: Vintage Elaborate Floral Pearl Statement Choker | D202: Ornate gold-tone floral centerpiece with pearl and purple stone accents. | G202: 55 | J202: =IF(AND(G202<>"",I202<>""),G202-I202,"") | K202: =IF(AND(G202<>"",G202<>0),J202/G202,"") | L202: Signature Haskell/Trifari style.
A203: NK_GT_ST_029 | B203: necklace | C203: Vintage Long Gold Tone Pink Cabochon Necklace | D203: Opera-length chain with pink lucite/glass cabochons in gold bezels. | E203: Gold Tone | G203: 37.5 | J203: =IF(AND(G203<>"",I203<>""),G203-I203,"") | K203: =IF(AND(G203<>"",G203<>0),J203/G203,"") | L203: 1970s flapper revival. Often by Monet or Napier.
A204: NK_GT_TQ_099 | B204: necklace | C204: Gold Flower Oval | D204: Triple-station gold oval flower with turquoise centers. | G204: 55 | J204: =IF(AND(G204<>"",I204<>""),G204-I204,"") | K204: =IF(AND(G204<>"",G204<>0),J204/G204,"") | L204: SKU: NK-GT-TQ-099
A205: NK_HG_ | B205: necklace | C205: Hammered Gold Disc: | D205: Bold Artisan Hammered Gold-Tone Graduated Disc Statement Necklace. | J205: =IF(AND(G205<>"",I205<>""),G205-I205,"") | K205: =IF(AND(G205<>"",G205<>0),J205/G205,"") | L205: SKU: NK-HG-
A206: NK_HM_FG_094 | B206: necklace | C206: Hematite Fringe | D206: Jagged gothic bib with faceted hematite-tone fringe. | G206: 43.5 | J206: =IF(AND(G206<>"",I206<>""),G206-I206,"") | K206: =IF(AND(G206<>"",G206<>0),J206/G206,"") | L206: SKU: NK-HM-FG-094
A207: NK_MC_ | B207: necklace | C207: Multi-Charm Silver Chain: | D207: Artisan Boho Style Silver Chain Necklace with Assorted Glass and Stone Charms. | J207: =IF(AND(G207<>"",I207<>""),G207-I207,"") | K207: =IF(AND(G207<>"",G207<>0),J207/G207,"") | L207: SKU: NK-MC-
A208: NK_MS_ | B208: necklace | C208: Multi-Strand Silver Chain: | D208: Minimalist Multi-Strand Layered Fine Silver-Tone Chain Necklace. | J208: =IF(AND(G208<>"",I208<>""),G208-I208,"") | K208: =IF(AND(G208<>"",G208<>0),J208/G208,"") | L208: SKU: NK-MS-
A209: NK_MX_BK_093 | B209: necklace | C209: Geometric Block | D209: Red, silver & bronze tiered geometric block bib. | G209: 41.5 | J209: =IF(AND(G209<>"",I209<>""),G209-I209,"") | K209: =IF(AND(G209<>"",G209<>0),J209/G209,"") | L209: SKU: NK-MX-BK-093
...

Sheet Raw Materials
A1: Material ID | B1: Material Type | C1: Description | D1: Unit | E1: Quantity in Stock | F1: Cost per Unit | G1: Total Value | H1: Reorder Point | I1: Supplier | J1: Notes
A2: CHAIN_001 | B2: Chain | C2: 18" Gold Plated Chain | D2: inches | E2: 240 | F2: 0.5 | G2: =IF(AND(E2<>"",F2<>""),E2*F2,"")
A3: CHAIN_002 | B3: Chain | C3: 20" Sterling Silver Chain | D3: inches | E3: 180 | F3: 0.75 | G3: =IF(AND(E3<>"",F3<>""),E3*F3,"")
A4: GEM_001 | B4: Gemstone | C4: 4mm Moissanite | D4: pieces | E4: 50 | F4: 2 | G4: =IF(AND(E4<>"",F4<>""),E4*F4,"") | H4: 20
A5: GEM_002 | B5: Gemstone | C5: Cubic Zirconia 6mm | D5: pieces | E5: 75 | F5: 1.5 | G5: =IF(AND(E5<>"",F5<>""),E5*F5,"") | H5: 25
A6: WIRE_001 | B6: Wire | C6: 20g Silver Wire | D6: feet | E6: 100 | F6: 0.25 | G6: =IF(AND(E6<>"",F6<>""),E6*F6,"") | H6: 50

Sheet Image Management
A1: IMAGE MANAGEMENT & URL GENERATOR
A3: HOW TO ADD IMAGES TO YOUR INVENTORY
A4: OPTION 1: Upload to Shopify (or your website)
A5: 1. | B5: Upload your jewelry photo to Shopify
A6: 2. | B6: Copy the image URL (right-click image > Copy image address)
A7: 3. | B7: Paste the URL in the "Images" column in Finished Inventory
A9: OPTION 2: Upload to Google Drive (FREE)
A10: 1. | B10: Upload photo to Google Drive
A11: 2. | B11: Right-click > Share > Change to "Anyone with link"
A12: 3. | B12: Copy the shareable link
A13: 4. | B13: Convert the link using the tool below
A15: OPTION 3: Use Imgur (FREE)
A16: 1. | B16: Go to imgur.com
A17: 2. | B17: Click "New post" and upload your image
A18: 3. | B18: Right-click the image > Copy image address
A19: 4. | B19: Paste in the "Images" column
A22: GOOGLE DRIVE URL CONVERTER
A23: Paste Google Drive Share Link:
A24: Direct Image URL: | B24: =IF(B23="","",IF(ISNUMBER(SEARCH("drive.google.com",B23)),"https://drive.google.com/uc?export=view&id=" & MID(B23,FIND("/d/",B23)+3,FIND("/view",B23)-FIND("/d/",B23)-3),"Invalid Google Drive link"))
A25: Copy the Direct Image URL above and paste it into your Finished Inventory "Images" column
A28: AUTO URL GENERATOR (For Bulk Upload)
A29: Your Base URL Pattern: | B29: https://cdn.shopify.com/s/files/1/0936/8656/3183/files/
A30: Instructions: | B30: 1. Update the base URL above if needed 2. Use the table below to generate URLs
A32: SKU | B32: Filename | C32: Generated URL | D32: Copy to Finished Inventory
C33: =IF(B33="","",$B$29&B33) | D33: ← Copy this URL to Finished Inventory
C34: =IF(B34="","",$B$29&B34) | D34: ← Copy this URL to Finished Inventory
C35: =IF(B35="","",$B$29&B35) | D35: ← Copy this URL to Finished Inventory
C36: =IF(B36="","",$B$29&B36) | D36: ← Copy this URL to Finished Inventory
C37: =IF(B37="","",$B$29&B37) | D37: ← Copy this URL to Finished Inventory
C38: =IF(B38="","",$B$29&B38) | D38: ← Copy this URL to Finished Inventory
C39: =IF(B39="","",$B$29&B39) | D39: ← Copy this URL to Finished Inventory
C40: =IF(B40="","",$B$29&B40) | D40: ← Copy this URL to Finished Inventory
C41: =IF(B41="","",$B$29&B41) | D41: ← Copy this URL to Finished Inventory
C42: =IF(B42="","",$B$29&B42) | D42: ← Copy this URL to Finished Inventory
C43: =IF(B43="","",$B$29&B43) | D43: ← Copy this URL to Finished Inventory
C44: =IF(B44="","",$B$29&B44) | D44: ← Copy this URL to Finished Inventory
... C52: =IF(B52="","",$B$29&B52) | D52: ← Copy this URL to Finished Inventory

Sheet Spool Tracker
A1: Spool ID | B1: Material Type | C1: Description | D1: Original Length | E1: Current Length | F1: Used | G1: Unit | H1: Cost per Unit | I1: Remaining Value | J1: Date Added | K1: Notes
A2: SPOOL_001 | B2: Chain | C2: 18" Gold Chain Spool | D2: 500 | E2: 240 | F2: =IF(AND(D2<>"",E2<>""),D2-E2,"") | G2: inches | H2: 0.5 | I2: =IF(AND(E2<>"",H2<>""),E2*H2,"") | J2: 2025-01-01 | K2: Main supplier spool
A3: SPOOL_002 | B3: Chain | C3: 20" Silver Chain Spool | D3: 400 | E3: 180 | F3: =IF(AND(D3<>"",E3<>""),D3-E3,"") | G3: inches | H3: 0.75 | I3: =IF(AND(E3<>"",H3<>""),E3*H3,"") | J3: 2025-01-01
A4: SPOOL_003 | B4: Wire | C4: 20g Silver Wire Spool | D4: 200 | E4: 100 | F4: =IF(AND(D4<>"",E4<>""),D4-E4,"") | G4: feet | H4: 0.25 | I4: =IF(AND(E4<>"",H4<>""),E4*H4,"") | J4: 2025-01-01

Sheet Usage Log
A1: Date | B1: Spool ID | C1: Material Used | D1: Amount Used | E1: Unit | F1: Used For (SKU) | G1: Notes
A2: INSTRUCTIONS: When you cut from a spool, log it here. Then manually update the "Current Length" in the Spool Tracker sheet.

Sheet Bundle Builder
A1: CUSTOM BUNDLE BUILDER
A2: Enter SKUs below to build a custom bundle. Prices will auto-calculate.
A3: Bundle Name: | C3: Target Price: | E3: Bundle Discount %:
A5: # | B5: SKU | C5: Item Name | D5: Category | E5: Price | F5: Include? | G5: Line Total
A6: 1 | C6: =IFERROR(VLOOKUP(B6,'Finished Inventory'!A:C,3,FALSE()),"") | D6: =IFERROR(VLOOKUP(B6,'Finished Inventory'!A:B,2,FALSE()),"") | E6: =IFERROR(VLOOKUP(B6,'Finished Inventory'!A:G,7,FALSE()),"") | F6: Yes | G6: =IF(F6="Yes",E6,0)
A7: 2 | C7: =IFERROR(VLOOKUP(B7,'Finished Inventory'!A:C,3,FALSE()),"") | D7: =IFERROR(VLOOKUP(B7,'Finished Inventory'!A:B,2,FALSE()),"") | E7: =IFERROR(VLOOKUP(B7,'Finished Inventory'!A:G,7,FALSE()),"") | F7: Yes | G7: =IF(F7="Yes",E7,0)
A8: 3 | C8: =IFERROR(VLOOKUP(B8,'Finished Inventory'!A:C,3,FALSE()),"") | D8: =IFERROR(VLOOKUP(B8,'Finished Inventory'!A:B,2,FALSE()),"") | E8: =IFERROR(VLOOKUP(B8,'Finished Inventory'!A:G,7,FALSE()),"") | F8: Yes | G8: =IF(F8="Yes",E8,0)
A9: 4 | C9: =IFERROR(VLOOKUP(B9,'Finished Inventory'!A:C,3,FALSE()),"") | D9: =IFERROR(VLOOKUP(B9,'Finished Inventory'!A:B,2,FALSE()),"") | E9: =IFERROR(VLOOKUP(B9,'Finished Inventory'!A:G,7,FALSE()),"") | F9: Yes | G9: =IF(F9="Yes",E9,0)
A10: 5 | C10: =IFERROR(VLOOKUP(B10,'Finished Inventory'!A:C,3,FALSE()),"") | D10: =IFERROR(VLOOKUP(B10,'Finished Inventory'!A:B,2,FALSE()),"") | E10: =IFERROR(VLOOKUP(B10,'Finished Inventory'!A:G,7,FALSE()),"") | F10: Yes | G10: =IF(F10="Yes",E10,0)
A11: 6 | C11: =IFERROR(VLOOKUP(B11,'Finished Inventory'!A:C,3,FALSE()),"") | D11: =IFERROR(VLOOKUP(B11,'Finished Inventory'!A:B,2,FALSE()),"") | E11: =IFERROR(VLOOKUP(B11,'Finished Inventory'!A:G,7,FALSE()),"") | F11: Yes | G11: =IF(F11="Yes",E11,0)
A12: 7 | C12: =IFERROR(VLOOKUP(B12,'Finished Inventory'!A:C,3,FALSE()),"") | D12: =IFERROR(VLOOKUP(B12,'Finished Inventory'!A:B,2,FALSE()),"") | E12: =IFERROR(VLOOKUP(B12,'Finished Inventory'!A:G,7,FALSE()),"") | F12: Yes | G12: =IF(F12="Yes",E12,0)
A13: 8 | C13: =IFERROR(VLOOKUP(B13,'Finished Inventory'!A:C,3,FALSE()),"") | D13: =IFERROR(VLOOKUP(B13,'Finished Inventory'!A:B,2,FALSE()),"") | E13: =IFERROR(VLOOKUP(B13,'Finished Inventory'!A:G,7,FALSE()),"") | F13: Yes | G13: =IF(F13="Yes",E13,0)
A14: 9 | C14: =IFERROR(VLOOKUP(B14,'Finished Inventory'!A:C,3,FALSE()),"") | D14: =IFERROR(VLOOKUP(B14,'Finished Inventory'!A:B,2,FALSE()),"") | E14: =IFERROR(VLOOKUP(B14,'Finished Inventory'!A:G,7,FALSE()),"") | F14: Yes | G14: =IF(F14="Yes",E14,0)
A15: 10 | C15: =IFERROR(VLOOKUP(B15,'Finished Inventory'!A:C,3,FALSE()),"") | D15: =IFERROR(VLOOKUP(B15,'Finished Inventory'!A:B,2,FALSE()),"") | E15: =IFERROR(VLOOKUP(B15,'Finished Inventory'!A:G,7,FALSE()),"") | F15: Yes | G15: =IF(F15="Yes",E15,0)
A16: 11 | C16: =IFERROR(VLOOKUP(B16,'Finished Inventory'!A:C,3,FALSE()),"") | D16: =IFERROR(VLOOKUP(B16,'Finished Inventory'!A:B,2,FALSE()),"") | E16: =IFERROR(VLOOKUP(B16,'Finished Inventory'!A:G,7,FALSE()),"") | F16: Yes | G16: =IF(F16="Yes",E16,0)
A17: 12 | C17: =IFERROR(VLOOKUP(B17,'Finished Inventory'!A:C,3,FALSE()),"") | D17: =IFERROR(VLOOKUP(B17,'Finished Inventory'!A:B,2,FALSE()),"") | E17: =IFERROR(VLOOKUP(B17,'Finished Inventory'!A:G,7,FALSE()),"") | F17: Yes | G17: =IF(F17="Yes",E17,0)
... A25: 20 | C25: =IFERROR(VLOOKUP(B25,'Finished Inventory'!A:C,3,FALSE()),"") | D25: =IFERROR(VLOOKUP(B25,'Finished Inventory'!A:B,2,FALSE()),"") | E25: =IFERROR(VLOOKUP(B25,'Finished Inventory'!A:G,7,FALSE()),"") | F25: Yes | G25: =IF(F25="Yes",E25,0)
E27: Subtotal: | G27: =SUM(G6:G25)
E28: Discount: | G28: =G27*F3
E29: Bundle Total: | G29: =G27-G28

Sheet Search & Filter
A1: SEARCH & FILTER
A3: Filter Criteria:
A4: Category:
A5: Metal Type:
A6: Price Range Min:
A7: Price Range Max:
A8: Search Text:
A10: TIP: Use Excel's built-in Filter (Data > Filter) on the Finished Inventory sheet for advanced filtering.
A12: QUICK STATS
A13: Total Items: | B13: =COUNTA('Finished Inventory'!A:A)-1
A14: Total Inventory Value: | B14: =SUMIF('Finished Inventory'!G:G,">0",'Finished Inventory'!G:G)
A15: Average Price: | B15: =AVERAGEIF('Finished Inventory'!G:G,">0",'Finished Inventory'!G:G)
A17: Items by Category:
A18: Necklace: | B18: =COUNTIF('Finished Inventory'!B:B,"necklace")
A19: Bracelet: | B19: =COUNTIF('Finished Inventory'!B:B,"bracelet")
A20: Earring: | B20: =COUNTIF('Finished Inventory'!B:B,"earring")
A21: Ring: | B21: =COUNTIF('Finished Inventory'!B:B,"ring")
A22: Set: | B22: =COUNTIF('Finished Inventory'!B:B,"set")

Sheet Image Upload Guide
A1: 📸 QUICK IMAGE UPLOAD GUIDE
A3: EASIEST METHOD: Google Drive (100% FREE)
A5: 1. Create a folder in Google Drive for jewelry images
A6: 2. Upload all your jewelry photos to that folder
A7: 3. For each photo:
A8: • Right-click the image > Share
A9: • Change to "Anyone with the link"
A10: • Click "Copy link"
A11: • Go to "Image Management" sheet
A12: • Paste in the Google Drive URL Converter
A13: • Copy the generated Direct Image URL
A14: • Paste in your Finished Inventory "Images" column
... A40: ✓ Dropbox (2GB free)
